notebook_as_pdf_updated/__init__.py
notebook_as_pdf_updated-0.5.1.dist-info/LICENSE
notebook_as_pdf_updated-0.5.1.dist-info/METADATA
notebook_as_pdf_updated-0.5.1.dist-info/WHEEL
notebook_as_pdf_updated-0.5.1.dist-info/entry_points.txt
notebook_as_pdf_updated-0.5.1.dist-info/top_level.txt
notebook_as_pdf_updated-0.5.1.dist-info/RECORD
