Metadata-Version: 2.1
Name: notebook-as-pdf-updated
Version: 0.5.1
Summary: Jupyter extension to export notebooks as PDFs
Home-page: https://github.com/betatim/notebook-as-pdf
Author: Abirami R
License: BSD3
Keywords: jupyter pdf export bundler
Platform: UNKNOWN
Requires-Python: >=3.7
License-File: LICENSE
Requires-Dist: PyPDF2
Requires-Dist: nbconvert
Requires-Dist: pyppeteer
